[
  {
    "english": "spray",
    "pron": "spreɪ",
    "kana": "スプレイ",
    "hinshi": "動詞 / 名詞",
    "ld_pos": "動詞",
    "ld_etym": "中期オランダ語 sprayen（まき散らす）",
    "ld_level": "準2級",
    "badges": ["中学生〜", "英検準2級", "CEFR B1", "頻出語"],
    "meaning_main": "（霧状に)吹きかける ／ スプレー ／ しぶき",
    "description": "spray（スプレイ）の意味は「（霧状に)吹きかける・スプレー」。spray water の使い方、語源、例文やクイズで解説。",
    "keywords": ["spray 意味", "spray 使い方", "spray water", "スプレー 英語", "spray 例文"],
    "meanings": [
      { "hinshi": "【動詞】（霧状に)吹きかける・噴霧する", "note": "液体を細かく散らしてかける。" },
      { "hinshi": "【名詞】スプレー・噴霧器", "note": "hair spray（ヘアスプレー)。" },
      { "hinshi": "【名詞】しぶき・水けむり", "note": "the spray of the waves（波しぶき)。" }
    ],
    "usages": [
      { "title": "① 吹きかける（spray）", "desc": "霧状にかける。", "example_en": "She sprayed water on the plants.", "example_ja": "彼女は植物に水を吹きかけた。" },
      { "title": "② スプレー（名詞）", "desc": "噴霧式の製品。", "example_en": "He used insect spray.", "example_ja": "彼は虫よけスプレーを使った。" },
      { "title": "③ しぶき（the spray）", "desc": "波などの細かい水。", "example_en": "I felt the spray of the sea.", "example_ja": "私は海のしぶきを感じた。" }
    ],
    "warn": [
      "spray は「（霧状に)吹きかける・スプレー・しぶき」。spray A on B / spray B with A の形",
      "hair spray（ヘアスプレー）、insect spray（虫よけスプレー）など"
    ],
    "etym_note": "中期オランダ語 sprayen（まき散らす）に由来する。「液体を細かく散らす＝噴霧する」が基本義で、名詞「スプレー・しぶき」も生まれた。",
    "etym_chain": [
      { "node": "sprayen", "sub": "まき散らす", "era": "中期オランダ語" },
      { "node": "spray", "sub": "吹きかける", "era": "近代英語" },
      { "node": "spray", "sub": "吹きかける・スプレー", "era": "現代英語" }
    ],
    "phrases": [
      { "en": "spray water", "ja": "水を吹きかける" },
      { "en": "hair spray", "ja": "ヘアスプレー" },
      { "en": "insect spray", "ja": "虫よけスプレー" },
      { "en": "a spray bottle", "ja": "スプレーボトル" },
      { "en": "spray paint", "ja": "スプレー塗料" },
      { "en": "sea spray", "ja": "波しぶき" }
    ],
    "related": [
      { "en": "splash", "ja": "（水を)はねかける" },
      { "en": "sprinkle", "ja": "（パラパラと)まく" },
      { "en": "mist", "ja": "霧" },
      { "en": "shower", "ja": "シャワー・にわか雨" }
    ],
    "faq": [
      { "q": "spray にはどんな意味がある？", "a": "「（霧状に)吹きかける（動詞)」「スプレー・噴霧器（名詞)」「しぶき・水けむり」などです。" },
      { "q": "「水を吹きかける」は英語で？", "a": "spray water (on ～) と言います。" }
    ],
    "quiz": [
      { "q": "\"She ___ perfume on her neck.\"（吹きかけた）の空所に入るのは？", "A": "sprayed", "B": "splashed", "C": "spread", "D": "sprinkled", "correct": "A" },
      { "q": "「ヘアスプレー」を表すのはどれ？", "A": "hair spray", "B": "spray paint", "C": "a spray bottle", "D": "sea spray", "correct": "A" }
    ]
  },
  {
    "english": "sprint",
    "pron": "sprɪnt",
    "kana": "スプリント",
    "hinshi": "動詞 / 名詞",
    "ld_pos": "動詞",
    "ld_etym": "古ノルド語 spretta（跳ねる)",
    "ld_level": "準2級",
    "badges": ["高校〜", "英検準2級", "CEFR B2", "頻出語"],
    "meaning_main": "全力疾走する ／ 短距離走",
    "description": "sprint（スプリント）の意味は「全力疾走する・短距離走」。sprint to の使い方、run との違い、語源、例文やクイズで解説。",
    "keywords": ["sprint 意味", "sprint 使い方", "sprint run 違い", "短距離走 英語", "sprint 例文"],
    "meanings": [
      { "hinshi": "【動詞】全力疾走する・短距離を全速で走る", "note": "短い距離を全力で走る。" },
      { "hinshi": "【名詞】短距離走・全力疾走", "note": "the 100-meter sprint（100m走)。" }
    ],
    "usages": [
      { "title": "① 全力疾走する（sprint）", "desc": "短距離を全速で走る。", "example_en": "He sprinted to catch the bus.", "example_ja": "彼はバスに乗ろうと全力疾走した。" },
      { "title": "② 短距離走（a sprint）", "desc": "「短距離レース」。", "example_en": "She won the 100-meter sprint.", "example_ja": "彼女は100m走で優勝した。" },
      { "title": "③ run との違い", "desc": "sprint は「（短く)全力で走る」、run は「走る」一般。", "example_en": "He sprinted the last 100 meters.", "example_ja": "彼は最後の100mを全力疾走した。" }
    ],
    "warn": [
      "sprint は「（短距離を)全力で走る」、jog は「ゆっくり走る」、run は「走る」一般",
      "「短距離走者」は a sprinter"
    ],
    "etym_note": "古ノルド語 spretta（跳ねる・勢いよく動く）に由来するとされる。「（短く)勢いよく全力で走る」という意味で使われる。",
    "etym_chain": [
      { "node": "spretta", "sub": "跳ねる", "era": "古ノルド語" },
      { "node": "sprint", "sub": "全力疾走する", "era": "19世紀英語" },
      { "node": "sprint", "sub": "全力疾走・短距離走", "era": "現代英語" }
    ],
    "phrases": [
      { "en": "sprint to", "ja": "～へ全力疾走する" },
      { "en": "the 100-meter sprint", "ja": "100メートル走" },
      { "en": "a final sprint", "ja": "ラストスパート" },
      { "en": "break into a sprint", "ja": "急に全力で走り出す" },
      { "en": "a sprinter", "ja": "短距離走者" },
      { "en": "sprint for the finish", "ja": "ゴールへ全力疾走する" }
    ],
    "related": [
      { "en": "run", "ja": "走る" },
      { "en": "jog", "ja": "ジョギングする" },
      { "en": "dash", "ja": "突進する" },
      { "en": "race", "ja": "競走" }
    ],
    "faq": [
      { "q": "sprint と run の違いは？", "a": "sprint は「（短距離を)全力で走る」、run は「走る」一般です。jog は「ゆっくり走る」です。" },
      { "q": "「短距離走者」は英語で？", "a": "a sprinter です。" }
    ],
    "quiz": [
      { "q": "\"He ___ to catch the train.\"（全力疾走した）の空所に入るのは？", "A": "sprinted", "B": "jogged", "C": "walked", "D": "crawled", "correct": "A" },
      { "q": "「100メートル走」を表すのはどれ？", "A": "the 100-meter sprint", "B": "a final sprint", "C": "a sprinter", "D": "break into a sprint", "correct": "A" }
    ]
  },
  {
    "english": "squirrel",
    "pron": "ˈskwɜːrəl",
    "kana": "スクワーレル",
    "hinshi": "名詞",
    "ld_pos": "名詞",
    "ld_etym": "ギリシャ語 skiouros（影の尾）",
    "ld_level": "3級",
    "badges": ["中学生〜", "英検3級", "CEFR A2", "基本語"],
    "meaning_main": "リス",
    "description": "squirrel（スクワーレル）の意味は「リス」。語源（影の尾)、squirrel away の使い方、例文やクイズで解説。",
    "keywords": ["squirrel 意味", "squirrel 使い方", "リス 英語", "squirrel away", "squirrel 例文"],
    "meanings": [
      { "hinshi": "【名詞】リス", "note": "大きな尾を持ち、木の実を食べる小動物。" }
    ],
    "usages": [
      { "title": "① リス（名詞）", "desc": "木に住む小動物。", "example_en": "A squirrel ran up the tree.", "example_ja": "リスが木を駆け上がった。" },
      { "title": "② どんぐりをためる", "desc": "リスは食べ物をため込む習性がある。", "example_en": "Squirrels gather nuts for winter.", "example_ja": "リスは冬に備えて木の実を集める。" },
      { "title": "③ ため込む（squirrel away）", "desc": "「（リスのように)こっそりため込む」。", "example_en": "She squirreled away some money.", "example_ja": "彼女はお金をこっそりため込んだ。" }
    ],
    "warn": [
      "発音は「スクワーレル（ˈskwɜːrəl）」。英米でやや異なる",
      "squirrel away は「（リスのように)こっそりため込む・蓄える」"
    ],
    "etym_note": "ギリシャ語 skiouros（skia＝影 + oura＝尾＝影の尾）に由来し、ラテン語・古フランス語を経て英語に入った。「（大きな尾で)日陰を作る動物」という発想に基づく。",
    "etym_chain": [
      { "node": "skiouros", "sub": "影の尾", "era": "ギリシャ語" },
      { "node": "esquirel", "sub": "リス", "era": "古フランス語" },
      { "node": "squirrel", "sub": "リス", "era": "現代英語" }
    ],
    "phrases": [
      { "en": "squirrel away", "ja": "こっそりため込む" },
      { "en": "a gray squirrel", "ja": "灰色リス" },
      { "en": "a flying squirrel", "ja": "ムササビ・モモンガ" },
      { "en": "a squirrel's nest", "ja": "リスの巣" },
      { "en": "gather nuts", "ja": "木の実を集める" },
      { "en": "a baby squirrel", "ja": "リスの赤ちゃん" }
    ],
    "related": [
      { "en": "rabbit", "ja": "ウサギ" },
      { "en": "mouse", "ja": "ネズミ" },
      { "en": "nut", "ja": "木の実・ナッツ" },
      { "en": "tail", "ja": "しっぽ" }
    ],
    "faq": [
      { "q": "squirrel away の意味は？", "a": "「（リスがどんぐりをためるように)こっそりため込む・蓄える」という意味の表現です。" },
      { "q": "squirrel の語源は？", "a": "ギリシャ語 skiouros（影の尾）に由来し、「大きな尾を持つ動物」という発想からきています。" }
    ],
    "quiz": [
      { "q": "\"A ___ buried a nut in the garden.\"（リス）の空所に入るのは？", "A": "squirrel", "B": "squid", "C": "squeeze", "D": "square", "correct": "A" },
      { "q": "「こっそりため込む」を表すのはどれ？", "A": "squirrel away", "B": "a gray squirrel", "C": "a squirrel's nest", "D": "gather nuts", "correct": "A" }
    ]
  },
  {
    "english": "stack",
    "pron": "stæk",
    "kana": "スタック",
    "hinshi": "名詞 / 動詞",
    "ld_pos": "名詞",
    "ld_etym": "古ノルド語 stakkr（干し草の山）",
    "ld_level": "準2級",
    "badges": ["高校〜", "英検準2級", "CEFR B1", "頻出語"],
    "meaning_main": "積み重ね ／ 山 ／ 積み重ねる",
    "description": "stack（スタック）の意味は「積み重ね・山・積み重ねる」。a stack of の使い方、pile との違い、語源、例文やクイズで解説。",
    "keywords": ["stack 意味", "stack 使い方", "a stack of", "stack pile 違い", "stack 例文"],
    "meanings": [
      { "hinshi": "【名詞】（きちんと積んだ)積み重ね・山", "note": "a stack of books（本の山)。" },
      { "hinshi": "【動詞】積み重ねる", "note": "stack the chairs（いすを積み重ねる)。" }
    ],
    "usages": [
      { "title": "① ～の山（a stack of）", "desc": "「積み重なった～」。", "example_en": "There was a stack of papers on the desk.", "example_ja": "机の上に書類の山があった。" },
      { "title": "② 積み重ねる（stack）", "desc": "きちんと重ねる。", "example_en": "Please stack the boxes here.", "example_ja": "箱をここに積み重ねて。" },
      { "title": "③ pile との違い", "desc": "stack は「（きちんと)積んだ山」、pile は「（雑然と)積んだ山」。", "example_en": "a neat stack / a messy pile", "example_ja": "きれいな積み重ね／乱雑な山" }
    ],
    "warn": [
      "stack は「（きちんと積んだ)山」、pile は「（雑然と積んだ)山」というニュアンス差",
      "a stack of ～（～の山）"
    ],
    "etym_note": "古ノルド語 stakkr（干し草の山）に由来する。「（積み上げた)山」が基本義で、「積み重ねる」の動詞も生まれた。",
    "etym_chain": [
      { "node": "stakkr", "sub": "干し草の山", "era": "古ノルド語" },
      { "node": "stack", "sub": "積み重ね", "era": "中英語" },
      { "node": "stack", "sub": "積み重ね・積み重ねる", "era": "現代英語" }
    ],
    "phrases": [
      { "en": "a stack of", "ja": "～の山・積み重ね" },
      { "en": "stack up", "ja": "積み上がる・積み上げる" },
      { "en": "a stack of books", "ja": "本の山" },
      { "en": "stacks of", "ja": "たくさんの～" },
      { "en": "neatly stacked", "ja": "きちんと積まれた" },
      { "en": "stack the dishes", "ja": "皿を重ねる" }
    ],
    "related": [
      { "en": "pile", "ja": "（雑然とした)山" },
      { "en": "heap", "ja": "（乱雑な)山" },
      { "en": "layer", "ja": "層" },
      { "en": "pile up", "ja": "積み上がる" }
    ],
    "faq": [
      { "q": "stack と pile の違いは？", "a": "stack は「（きちんと整えて積んだ)山」、pile は「（雑然と積んだ)山」というニュアンスです。" },
      { "q": "a stack of の意味は？", "a": "「（積み重なった)～の山」という意味です。a stack of papers（書類の山）のように使います。" }
    ],
    "quiz": [
      { "q": "\"There's a ___ of books on the desk.\"（山）の空所に入るのは？", "A": "stack", "B": "stuck", "C": "stick", "D": "stock", "correct": "A" },
      { "q": "「きちんと積まれた」を表すのはどれ？", "A": "neatly stacked", "B": "stack up", "C": "stacks of", "D": "a stack of", "correct": "A" }
    ]
  },
  {
    "english": "stale",
    "pron": "steɪl",
    "kana": "ステイル",
    "hinshi": "形容詞",
    "ld_pos": "形容詞",
    "ld_etym": "古フランス語 estale（古くなった）",
    "ld_level": "準2級",
    "badges": ["高校〜", "英検準2級", "CEFR B2", "頻出語"],
    "meaning_main": "（食品が)古くなった ／ 新鮮でない ／ 陳腐な",
    "description": "stale（ステイル）の意味は「（食品が)古くなった・新鮮でない」。fresh との対、stale bread の使い方、語源、例文やクイズで解説。",
    "keywords": ["stale 意味", "stale 使い方", "stale fresh 違い", "stale bread", "stale 例文"],
    "meanings": [
      { "hinshi": "【形容詞】（パンなどが)古くなった・新鮮でない", "note": "時間がたって味・質が落ちた。反対は fresh。" },
      { "hinshi": "【形容詞】（空気が)よどんだ／陳腐な", "note": "stale air（よどんだ空気)、stale jokes（古くさい冗談)。" }
    ],
    "usages": [
      { "title": "① 古くなったパン（stale bread）", "desc": "新鮮でなくなったパン。", "example_en": "The bread is stale.", "example_ja": "そのパンは古くなっている。" },
      { "title": "② fresh との対", "desc": "stale（古い)⇔ fresh（新鮮な）。", "example_en": "fresh bread / stale bread", "example_ja": "新鮮なパン／古くなったパン" },
      { "title": "③ よどんだ空気（stale air）", "desc": "「新鮮でない空気」。", "example_en": "The room smelled of stale air.", "example_ja": "部屋はよどんだ空気のにおいがした。" }
    ],
    "warn": [
      "stale（古くなった・新鮮でない）⇔ fresh（新鮮な）。パン・空気・冗談などに使う",
      "「（食品が)腐った」は rotten / spoiled。stale は「古くなって味が落ちた」程度"
    ],
    "etym_note": "古フランス語 estale（古くなった・落ち着いた）に由来する。「（時間がたって)新鮮さを失った」という意味で使われる。",
    "etym_chain": [
      { "node": "estale", "sub": "古くなった", "era": "古フランス語" },
      { "node": "stale", "sub": "新鮮でない", "era": "中英語" },
      { "node": "stale", "sub": "古くなった・新鮮でない", "era": "現代英語" }
    ],
    "phrases": [
      { "en": "stale bread", "ja": "古くなったパン" },
      { "en": "stale air", "ja": "よどんだ空気" },
      { "en": "go stale", "ja": "古くなる・新鮮さを失う" },
      { "en": "stale news", "ja": "古いニュース" },
      { "en": "a stale joke", "ja": "古くさい冗談" },
      { "en": "stale coffee", "ja": "気の抜けたコーヒー" }
    ],
    "related": [
      { "en": "fresh", "ja": "新鮮な" },
      { "en": "old", "ja": "古い" },
      { "en": "rotten", "ja": "腐った" },
      { "en": "moldy", "ja": "かびの生えた" }
    ],
    "faq": [
      { "q": "stale の反対語は？", "a": "fresh（新鮮な）です。stale bread（古くなったパン）⇔ fresh bread（新鮮なパン）。" },
      { "q": "stale と rotten の違いは？", "a": "stale は「（時間がたって)新鮮さを失った・古くなった」、rotten は「腐った」です。stale のほうが程度が軽いです。" }
    ],
    "quiz": [
      { "q": "\"This bread is hard and ___.\"（古くなった）の空所に入るのは？", "A": "stale", "B": "fresh", "C": "sweet", "D": "soft", "correct": "A" },
      { "q": "stale の反対語はどれ？", "A": "fresh", "B": "rotten", "C": "old", "D": "moldy", "correct": "A" }
    ]
  },
  {
    "english": "starve",
    "pron": "stɑːrv",
    "kana": "スターブ",
    "hinshi": "動詞",
    "ld_pos": "動詞",
    "ld_etym": "古英語 steorfan（死ぬ）",
    "ld_level": "準2級",
    "badges": ["高校〜", "英検準2級", "CEFR B1", "頻出語"],
    "meaning_main": "飢える ／ 餓死する ／ 腹ぺこである",
    "description": "starve（スターブ）の意味は「飢える・餓死する」。be starving の使い方、starvation との関係、語源、例文やクイズで解説。",
    "keywords": ["starve 意味", "starve 使い方", "be starving", "starvation", "starve 例文"],
    "meanings": [
      { "hinshi": "【動詞】飢える・餓死する", "note": "食べ物がなくて苦しむ・死ぬ。" },
      { "hinshi": "【動詞】（口語)とても空腹である", "note": "I'm starving.（おなかがぺこぺこだ)。" }
    ],
    "usages": [
      { "title": "① 飢える・餓死する（starve）", "desc": "食べ物がなくて苦しむ。", "example_en": "Many people starved during the war.", "example_ja": "戦争中に多くの人が飢えた。" },
      { "title": "② 腹ぺこだ（be starving）", "desc": "口語で「とても空腹」。", "example_en": "I'm starving! Let's eat.", "example_ja": "おなかぺこぺこ！食べよう。" },
      { "title": "③ starvation（飢餓）", "desc": "名詞。die of starvation（餓死する)。", "example_en": "They died of starvation.", "example_ja": "彼らは餓死した。" }
    ],
    "warn": [
      "be starving は口語で「とても空腹だ（おなかがぺこぺこ)」。文字どおり「餓死しそう」ではない",
      "名詞は starvation（飢餓）。die of starvation（餓死する)"
    ],
    "etym_note": "古英語 steorfan（死ぬ）に由来する。もとは「死ぬ」だったが、のちに「（飢えで)死ぬ＝飢える・餓死する」に意味が狭まった。ドイツ語 sterben（死ぬ）と同源。",
    "etym_chain": [
      { "node": "steorfan", "sub": "死ぬ", "era": "古英語" },
      { "node": "sterven", "sub": "死ぬ・飢える", "era": "中英語" },
      { "node": "starve", "sub": "飢える・餓死する", "era": "現代英語" }
    ],
    "phrases": [
      { "en": "be starving", "ja": "腹ぺこである" },
      { "en": "starve to death", "ja": "餓死する" },
      { "en": "die of starvation", "ja": "餓死する" },
      { "en": "starving children", "ja": "飢えた子どもたち" },
      { "en": "starve for", "ja": "～を渇望する" },
      { "en": "I could eat a horse.", "ja": "馬一頭食べられそうだ（とても空腹)" }
    ],
    "related": [
      { "en": "starvation", "ja": "飢餓" },
      { "en": "hungry", "ja": "空腹の" },
      { "en": "famine", "ja": "飢饉" },
      { "en": "feed", "ja": "食べさせる" }
    ],
    "faq": [
      { "q": "be starving の意味は？", "a": "口語で「とてもおなかがすいている（ぺこぺこ）」という意味です。文字どおり「餓死しそう」ではなく、強い空腹を表す誇張表現です。" },
      { "q": "starve の名詞は？", "a": "starvation（飢餓）です。die of starvation（餓死する）のように使います。" }
    ],
    "quiz": [
      { "q": "\"I'm ___! Let's get something to eat.\"（腹ぺこ）の空所に入るのは？", "A": "starving", "B": "starting", "C": "staring", "D": "staying", "correct": "A" },
      { "q": "「餓死する」を表すのはどれ？", "A": "starve to death", "B": "be starving", "C": "starve for", "D": "starving children", "correct": "A" }
    ]
  },
  {
    "english": "stool",
    "pron": "stuːl",
    "kana": "ストゥール",
    "hinshi": "名詞",
    "ld_pos": "名詞",
    "ld_etym": "古英語 stōl（いす)",
    "ld_level": "準2級",
    "badges": ["高校〜", "英検準2級", "CEFR B1", "頻出語"],
    "meaning_main": "（背もたれのない)いす ／ スツール",
    "description": "stool（ストゥール）の意味は「（背もたれのない)いす・スツール」。a bar stool の使い方、chair との違い、語源、例文やクイズで解説。",
    "keywords": ["stool 意味", "stool 使い方", "bar stool", "stool chair 違い", "stool 例文"],
    "meanings": [
      { "hinshi": "【名詞】（背もたれ・ひじ掛けのない)いす・スツール", "note": "一人用の小さないす。" }
    ],
    "usages": [
      { "title": "① スツール（a stool）", "desc": "背もたれのないいす。", "example_en": "She sat on a stool.", "example_ja": "彼女はスツールに座った。" },
      { "title": "② バースツール（a bar stool）", "desc": "バーカウンターの高いいす。", "example_en": "He sat on a bar stool.", "example_ja": "彼はバーの椅子に座った。" },
      { "title": "③ chair との違い", "desc": "stool は背もたれなし、chair は背もたれあり。", "example_en": "A stool has no back; a chair does.", "example_ja": "スツールには背もたれがなく、いすにはある。" }
    ],
    "warn": [
      "stool は「背もたれ・ひじ掛けのない小さないす」、chair は「背もたれのあるいす」",
      "a bar stool（バーの高いいす）、a piano stool（ピアノいす）"
    ],
    "etym_note": "古英語 stōl（いす・座）に由来し、ゲルマン祖語にさかのぼる。ドイツ語 Stuhl（いす）と同源。もとは「いす」全般だったが、のちに「背もたれのない小さないす」を指すようになった。",
    "etym_chain": [
      { "node": "stōl", "sub": "いす・座", "era": "古英語" },
      { "node": "stool", "sub": "いす", "era": "中英語" },
      { "node": "stool", "sub": "スツール", "era": "現代英語" }
    ],
    "phrases": [
      { "en": "a bar stool", "ja": "バーの高いいす" },
      { "en": "a piano stool", "ja": "ピアノいす" },
      { "en": "a kitchen stool", "ja": "台所用のスツール" },
      { "en": "sit on a stool", "ja": "スツールに座る" },
      { "en": "a folding stool", "ja": "折りたたみいす" },
      { "en": "a three-legged stool", "ja": "三脚のスツール" }
    ],
    "related": [
      { "en": "chair", "ja": "いす" },
      { "en": "seat", "ja": "座席" },
      { "en": "bench", "ja": "ベンチ" },
      { "en": "sofa", "ja": "ソファ" }
    ],
    "faq": [
      { "q": "stool と chair の違いは？", "a": "stool は「背もたれ・ひじ掛けのない小さないす」、chair は「背もたれのあるいす」です。" },
      { "q": "a bar stool とは？", "a": "「バーカウンター用の(脚の高い)いす」のことです。" }
    ],
    "quiz": [
      { "q": "\"He sat on a ___ at the counter.\"（スツール）の空所に入るのは？", "A": "stool", "B": "school", "C": "stoop", "D": "steel", "correct": "A" },
      { "q": "「バーの高いいす」を表すのはどれ？", "A": "a bar stool", "B": "a piano stool", "C": "a folding stool", "D": "a kitchen stool", "correct": "A" }
    ]
  },
  {
    "english": "stubborn",
    "pron": "ˈstʌbərn",
    "kana": "スタボーン",
    "hinshi": "形容詞",
    "ld_pos": "形容詞",
    "ld_etym": "中英語 stiborn（頑固な、由来不詳）",
    "ld_level": "準2級",
    "badges": ["高校〜", "英検準2級", "CEFR B2", "頻出語"],
    "meaning_main": "頑固な ／ 強情な ／ 手ごわい",
    "description": "stubborn（スタボーン）の意味は「頑固な・強情な」。as stubborn as a mule の使い方、flexible との対、語源、例文やクイズで解説。",
    "keywords": ["stubborn 意味", "stubborn 使い方", "stubborn as a mule", "頑固 英語", "stubborn 例文"],
    "meanings": [
      { "hinshi": "【形容詞】頑固な・強情な", "note": "自分の考えを変えない。" },
      { "hinshi": "【形容詞】（汚れなどが)落ちにくい・手ごわい", "note": "a stubborn stain（落ちにくいしみ)。" }
    ],
    "usages": [
      { "title": "① 頑固な（stubborn）", "desc": "考えを変えない。", "example_en": "He is too stubborn to apologize.", "example_ja": "彼は頑固すぎて謝らない。" },
      { "title": "② ロバのように頑固（as stubborn as a mule）", "desc": "「とても頑固」のたとえ。", "example_en": "She is as stubborn as a mule.", "example_ja": "彼女はとても頑固だ。" },
      { "title": "③ 落ちにくいしみ（a stubborn stain）", "desc": "「手ごわい汚れ」。", "example_en": "This is a stubborn stain.", "example_ja": "これは落ちにくいしみだ。" }
    ],
    "warn": [
      "stubborn は「頑固な・強情な（考えを変えない)」。よい意味の「粘り強い」は persistent / determined",
      "比喩で「（汚れ・問題が)落ちにくい・手ごわい」にも使う"
    ],
    "etym_note": "中英語 stiborn / stoburn（頑固な）に由来するが、その先の語源ははっきりしていない。「（意地を張って)頑固な」という意味で使われてきた。",
    "etym_chain": [
      { "node": "stiborn", "sub": "頑固な", "era": "中英語" },
      { "node": "stubborn", "sub": "頑固な", "era": "中英語" },
      { "node": "stubborn", "sub": "頑固な・強情な", "era": "現代英語" }
    ],
    "phrases": [
      { "en": "as stubborn as a mule", "ja": "ロバのように頑固" },
      { "en": "a stubborn person", "ja": "頑固な人" },
      { "en": "a stubborn stain", "ja": "落ちにくいしみ" },
      { "en": "stubborn refusal", "ja": "かたくなな拒否" },
      { "en": "too stubborn to ～", "ja": "頑固すぎて～しない" },
      { "en": "a stubborn attitude", "ja": "強情な態度" }
    ],
    "related": [
      { "en": "flexible", "ja": "柔軟な" },
      { "en": "determined", "ja": "決意の固い" },
      { "en": "persistent", "ja": "粘り強い" },
      { "en": "obstinate", "ja": "強情な" }
    ],
    "faq": [
      { "q": "stubborn は悪い意味？", "a": "「頑固な・強情な（融通がきかない)」というやや否定的な意味です。よい意味で「粘り強い」と言いたいときは persistent / determined を使います。" },
      { "q": "a stubborn stain の意味は？", "a": "「落ちにくいしみ（手ごわい汚れ）」という意味です。stubborn は物事が「手ごわい・しつこい」場合にも使えます。" }
    ],
    "quiz": [
      { "q": "\"He won't change his mind; he's very ___.\"（頑固な）の空所に入るのは？", "A": "stubborn", "B": "flexible", "C": "gentle", "D": "shy", "correct": "A" },
      { "q": "「とても頑固」のたとえはどれ？", "A": "as stubborn as a mule", "B": "a stubborn stain", "C": "stubborn refusal", "D": "a stubborn attitude", "correct": "A" }
    ]
  },
  {
    "english": "summary",
    "pron": "ˈsʌməri",
    "kana": "サマリー",
    "hinshi": "名詞",
    "ld_pos": "名詞",
    "ld_etym": "ラテン語 summa（合計・要点）",
    "ld_level": "準2級",
    "badges": ["高校〜", "英検準2級", "CEFR B1", "頻出語"],
    "meaning_main": "要約 ／ まとめ ／ 概要",
    "description": "summary（サマリー）の意味は「要約・まとめ」。in summary の使い方、summarize との関係、語源、例文やクイズで解説。",
    "keywords": ["summary 意味", "summary 使い方", "in summary", "summarize", "summary 例文"],
    "meanings": [
      { "hinshi": "【名詞】要約・まとめ・概要", "note": "要点を短くまとめたもの。" }
    ],
    "usages": [
      { "title": "① 要約（a summary）", "desc": "「要点のまとめ」。", "example_en": "Write a summary of the story.", "example_ja": "その話の要約を書きなさい。" },
      { "title": "② 要するに（in summary）", "desc": "「まとめると」。", "example_en": "In summary, the plan worked well.", "example_ja": "要するに、その計画はうまくいった。" },
      { "title": "③ summarize との関係", "desc": "動詞 summarize（要約する）⇔ 名詞 summary（要約）。", "example_en": "Can you summarize it in a short summary?", "example_ja": "それを短い要約にまとめられますか？" }
    ],
    "warn": [
      "summary は名詞「要約」、summarize は動詞「要約する」。品詞を区別する",
      "in summary は「要するに・まとめると」"
    ],
    "etym_note": "ラテン語 summa（合計・要点、summus＝最高の に由来）から来ている。「（全体の)要点をまとめたもの＝要約」を表す。sum（合計）と同語源。",
    "etym_chain": [
      { "node": "summa", "sub": "合計・要点", "era": "ラテン語" },
      { "node": "summary", "sub": "要約", "era": "中英語" },
      { "node": "summary", "sub": "要約・まとめ", "era": "現代英語" }
    ],
    "phrases": [
      { "en": "in summary", "ja": "要するに・まとめると" },
      { "en": "a brief summary", "ja": "簡単な要約" },
      { "en": "write a summary", "ja": "要約を書く" },
      { "en": "a summary of", "ja": "～の要約" },
      { "en": "a news summary", "ja": "ニュースの要約" },
      { "en": "give a summary", "ja": "概要を述べる" }
    ],
    "related": [
      { "en": "summarize", "ja": "要約する" },
      { "en": "outline", "ja": "概要" },
      { "en": "abstract", "ja": "要旨・抄録" },
      { "en": "overview", "ja": "概観" }
    ],
    "faq": [
      { "q": "summary と summarize の違いは？", "a": "summary は名詞「要約・まとめ」、summarize は動詞「要約する」です。" },
      { "q": "in summary の意味は？", "a": "「要するに・まとめると」という意味です。話の締めくくりに使います。" }
    ],
    "quiz": [
      { "q": "\"Write a short ___ of the article.\"（要約）の空所に入るのは？", "A": "summary", "B": "summarize", "C": "summer", "D": "summit", "correct": "A" },
      { "q": "「要するに」を表すのはどれ？", "A": "in summary", "B": "a brief summary", "C": "a news summary", "D": "give a summary", "correct": "A" }
    ]
  },
  {
    "english": "summit",
    "pron": "ˈsʌmɪt",
    "kana": "サミット",
    "hinshi": "名詞",
    "ld_pos": "名詞",
    "ld_etym": "ラテン語 summum（最高点）",
    "ld_level": "準2級",
    "badges": ["高校〜", "英検準2級", "CEFR B2", "頻出語"],
    "meaning_main": "頂上 ／ 首脳会談 ／ 絶頂",
    "description": "summit（サミット）の意味は「頂上・首脳会談」。reach the summit の使い方、語源、例文やクイズで解説。",
    "keywords": ["summit 意味", "summit 使い方", "reach the summit", "首脳会談 英語", "summit 例文"],
    "meanings": [
      { "hinshi": "【名詞】（山の)頂上・頂", "note": "山のいちばん高い所。" },
      { "hinshi": "【名詞】首脳会談・サミット", "note": "各国首脳の会議。a summit meeting。" }
    ],
    "usages": [
      { "title": "① 頂上に着く（reach the summit）", "desc": "「山頂に達する」。", "example_en": "They reached the summit at noon.", "example_ja": "彼らは正午に頂上に着いた。" },
      { "title": "② 首脳会談（a summit）", "desc": "「各国首脳の会議」。", "example_en": "World leaders met at the summit.", "example_ja": "世界の首脳がサミットで会った。" },
      { "title": "③ 絶頂（the summit of）", "desc": "「（成功などの)頂点」。", "example_en": "the summit of her career", "example_ja": "彼女のキャリアの絶頂" }
    ],
    "warn": [
      "summit は「（山の)頂上」「（各国首脳の)サミット・首脳会談」「絶頂」と幅広い",
      "発音は「サミット（ˈsʌmɪt）」。「頂上に達する」は reach the summit"
    ],
    "etym_note": "ラテン語 summum（最高点、summus＝最高の に由来）から、古フランス語 somet を経て英語に入った。「いちばん高い所＝頂上」を表す。summary（要約）と同じ語族。",
    "etym_chain": [
      { "node": "summum", "sub": "最高点", "era": "ラテン語" },
      { "node": "somet", "sub": "頂上", "era": "古フランス語" },
      { "node": "summit", "sub": "頂上・首脳会談", "era": "現代英語" }
    ],
    "phrases": [
      { "en": "reach the summit", "ja": "頂上に着く" },
      { "en": "a summit meeting", "ja": "首脳会談" },
      { "en": "the G7 summit", "ja": "G7サミット" },
      { "en": "the summit of", "ja": "～の頂点・絶頂" },
      { "en": "a mountain summit", "ja": "山頂" },
      { "en": "hold a summit", "ja": "首脳会談を開く" }
    ],
    "related": [
      { "en": "peak", "ja": "頂点・山頂" },
      { "en": "top", "ja": "てっぺん" },
      { "en": "mountain", "ja": "山" },
      { "en": "conference", "ja": "会議" }
    ],
    "faq": [
      { "q": "summit にはどんな意味がある？", "a": "「（山の)頂上」「（各国首脳の)サミット・首脳会談」「（成功などの)絶頂・頂点」など幅広い意味があります。" },
      { "q": "「頂上に達する」は英語で？", "a": "reach the summit と言います。reach the top も同義です。" }
    ],
    "quiz": [
      { "q": "\"They finally reached the ___ of the mountain.\"（頂上）の空所に入るのは？", "A": "summit", "B": "summary", "C": "summer", "D": "submit", "correct": "A" },
      { "q": "「首脳会談」を表すのはどれ？", "A": "a summit meeting", "B": "a mountain summit", "C": "reach the summit", "D": "the summit of", "correct": "A" }
    ]
  }
]
