[
  {
    "english": "scheme",
    "pron": "skiːm",
    "kana": "スキーム",
    "hinshi": "名詞 / 動詞",
    "ld_pos": "名詞",
    "ld_etym": "ギリシャ語 schēma（形・図）",
    "ld_level": "準1級",
    "badges": ["高校〜", "英検準1級", "CEFR B2", "頻出語"],
    "meaning_main": "計画・制度 ／ たくらみ ／ たくらむ",
    "description": "scheme（スキーム）の意味は「計画・制度／(悪い)たくらみ／たくらむ」。a pension scheme、scheme against の使い方、語源、例文やクイズで解説。",
    "keywords": ["scheme 意味", "pension scheme", "scheme against", "scheme 使い方", "scheme 例文"],
    "meanings": [
      { "hinshi": "【名詞】計画・制度・体系", "note": "(主に英)公的な計画や制度。" },
      { "hinshi": "【名詞】たくらみ・陰謀", "note": "(悪い)もくろみ。" },
      { "hinshi": "【動詞】たくらむ・陰謀を企てる", "note": "ひそかに計画する。" }
    ],
    "usages": [
      { "title": "① 制度（a pension scheme）", "desc": "公的な計画。", "example_en": "They joined the pension scheme.", "example_ja": "彼らは年金制度に加入した。" },
      { "title": "② たくらみ（a scheme）", "desc": "悪いもくろみ。", "example_en": "It was a scheme to make money.", "example_ja": "それは金もうけのたくらみだった。" },
      { "title": "③ たくらむ（scheme）", "desc": "陰謀を企てる。", "example_en": "They schemed to take over the company.", "example_ja": "彼らは会社の乗っ取りをたくらんだ。" }
    ],
    "warn": [
      "イギリス英語では「(公的な)計画・制度」(中立)、アメリカ英語では「たくらみ」(否定的)が中心",
      "color scheme(配色)、a scheme of things(物事の仕組み)などの表現もある"
    ],
    "etym_note": "ギリシャ語 schēma（形・図・体系)に由来する。「物事の形・図式＝計画・体系」が原義で、転じて「(ひそかな)たくらみ」の意味にもなった。",
    "etym_chain": [
      { "node": "schēma", "sub": "形・図", "era": "ギリシャ語" },
      { "node": "scheme", "sub": "計画・たくらみ", "era": "現代英語" }
    ],
    "phrases": [
      { "en": "a pension scheme", "ja": "年金制度" },
      { "en": "a color scheme", "ja": "配色" },
      { "en": "a clever scheme", "ja": "巧妙なたくらみ" },
      { "en": "scheme against", "ja": "〜に対して陰謀を企てる" },
      { "en": "a get-rich-quick scheme", "ja": "一獲千金のもくろみ" },
      { "en": "the scheme of things", "ja": "物事の仕組み" }
    ],
    "related": [
      { "en": "plan", "ja": "計画" },
      { "en": "plot", "ja": "陰謀" },
      { "en": "program", "ja": "計画・制度" },
      { "en": "conspire", "ja": "共謀する" }
    ],
    "faq": [
      { "q": "scheme は良い意味？悪い意味？", "a": "イギリス英語では「(公的な)計画・制度」と中立的、アメリカ英語では「たくらみ」と否定的に使われることが多いです。" },
      { "q": "a color scheme とは？", "a": "「配色・色の組み合わせ」という意味です。" }
    ],
    "quiz": [
      { "q": "\"The company set up a new pension ___.\"（制度）の空所に入るのは？", "A": "scheme", "B": "scene", "C": "scope", "D": "screen", "correct": "A" },
      { "q": "scheme の(悪い意味での)類義語は？", "A": "plot", "B": "honesty", "C": "truth", "D": "fact", "correct": "A" }
    ]
  },
  {
    "english": "scenario",
    "pron": "sɪˈnɑːrioʊ",
    "kana": "シナリオ",
    "hinshi": "名詞",
    "ld_pos": "名詞",
    "ld_etym": "イタリア語 scenario（舞台の筋書き）",
    "ld_level": "準1級",
    "badges": ["高校〜", "英検準1級", "CEFR B2", "頻出語"],
    "meaning_main": "想定される筋書き ／ シナリオ ／ 事態",
    "description": "scenario（シナリオ）の意味は「想定される筋書き・事態・シナリオ」。a worst-case scenario の使い方、語源、例文やクイズで解説。",
    "keywords": ["scenario 意味", "worst-case scenario", "scenario 想定", "scenario 使い方", "scenario 例文"],
    "meanings": [
      { "hinshi": "【名詞】想定される筋書き・事態・状況", "note": "起こりうる展開の見取り図。" },
      { "hinshi": "【名詞】（映画などの）脚本・筋書き", "note": "ストーリーの構成。" }
    ],
    "usages": [
      { "title": "① 想定（a scenario）", "desc": "起こりうる事態。", "example_en": "Imagine a scenario where you lose your job.", "example_ja": "仕事を失う事態を想像してみて。" },
      { "title": "② 最悪の事態（worst-case scenario）", "desc": "最悪の想定。", "example_en": "In the worst-case scenario, we lose everything.", "example_ja": "最悪の場合、すべてを失う。" },
      { "title": "③ 筋書き（a likely scenario）", "desc": "ありそうな展開。", "example_en": "That's the most likely scenario.", "example_ja": "それが最もありそうな筋書きだ。" }
    ],
    "warn": [
      "a worst-case / best-case scenario(最悪/最善の事態)が頻出",
      "複数形は scenarios。発音は「シナーリオウ(sɪˈnɑːrioʊ)」"
    ],
    "etym_note": "イタリア語 scenario（舞台の筋書き、ラテン語 scaena「舞台」由来)に由来する。「舞台の筋書き」から「(起こりうる)想定・事態」の意味に広がった。scene と同語源。",
    "etym_chain": [
      { "node": "scaena", "sub": "舞台", "era": "ラテン語" },
      { "node": "scenario", "sub": "筋書き・想定", "era": "現代英語" }
    ],
    "phrases": [
      { "en": "a worst-case scenario", "ja": "最悪の事態" },
      { "en": "a best-case scenario", "ja": "最善の事態" },
      { "en": "a likely scenario", "ja": "ありそうな展開" },
      { "en": "a possible scenario", "ja": "起こりうる事態" },
      { "en": "a nightmare scenario", "ja": "悪夢のような事態" },
      { "en": "imagine a scenario", "ja": "事態を想定する" }
    ],
    "related": [
      { "en": "situation", "ja": "状況" },
      { "en": "scenery", "ja": "風景" },
      { "en": "outcome", "ja": "結果" },
      { "en": "plot", "ja": "筋書き" }
    ],
    "faq": [
      { "q": "worst-case scenario の意味は？", "a": "「最悪の事態・最悪の場合に想定される展開」という意味です。" },
      { "q": "scenario の複数形は？", "a": "scenarios です。" }
    ],
    "quiz": [
      { "q": "\"Let's plan for the worst-case ___.\"（事態）の空所に入るのは？", "A": "scenario", "B": "scenery", "C": "scene", "D": "scent", "correct": "A" },
      { "q": "scenario に最も意味が近いのは？", "A": "situation", "B": "scenery", "C": "smell", "D": "stage", "correct": "A" }
    ]
  },
  {
    "english": "scapegoat",
    "pron": "ˈskeɪpɡoʊt",
    "kana": "スケープゴート",
    "hinshi": "名詞 / 動詞",
    "ld_pos": "名詞",
    "ld_etym": "escape（逃れる）+ goat（ヤギ）",
    "ld_level": "1級",
    "badges": ["大学〜", "英検1級", "CEFR C1", "難語"],
    "meaning_main": "身代わり ／ 責任を負わされる人",
    "description": "scapegoat（スケープゴート）の意味は「身代わり・(他人の罪の)責任を負わされる人」。make a scapegoat of の使い方、語源、例文やクイズで解説。",
    "keywords": ["scapegoat 意味", "make a scapegoat of", "scapegoat 身代わり", "scapegoat 使い方", "scapegoat 例文"],
    "meanings": [
      { "hinshi": "【名詞】身代わり・(他人の罪の)責任を負わされる人", "note": "他人の過失の責めを負わされる人。" },
      { "hinshi": "【動詞】〜を身代わりにする", "note": "責任を押しつける。" }
    ],
    "usages": [
      { "title": "① 身代わり（a scapegoat）", "desc": "責めを負わされる人。", "example_en": "He was made a scapegoat for the failure.", "example_ja": "彼はその失敗の身代わりにされた。" },
      { "title": "② 〜を身代わりにする（make a scapegoat of）", "desc": "責任を押しつける。", "example_en": "They made a scapegoat of the new employee.", "example_ja": "彼らは新入社員に責任をなすりつけた。" },
      { "title": "③ 責任転嫁（scapegoat）", "desc": "動詞でも使う。", "example_en": "Don't scapegoat the team.", "example_ja": "チームに責任を押しつけるな。" }
    ],
    "warn": [
      "make a scapegoat of ... / use ... as a scapegoat で「〜を身代わりにする」",
      "「(本来の責任者でない人に)罪・責めを負わせる人」"
    ],
    "etym_note": "escape（逃れる)+ goat（ヤギ)から作られた語。聖書で人々の罪を負わせて荒野に放たれたヤギの故事に由来し、「他人の罪を負わされる身代わり」を表す。",
    "etym_chain": [
      { "node": "(e)scape + goat", "sub": "罪を負って放たれるヤギ", "era": "近代英語" },
      { "node": "scapegoat", "sub": "身代わり", "era": "現代英語" }
    ],
    "phrases": [
      { "en": "make a scapegoat of", "ja": "〜を身代わりにする" },
      { "en": "use as a scapegoat", "ja": "身代わりに使う" },
      { "en": "a convenient scapegoat", "ja": "都合のよい身代わり" },
      { "en": "become a scapegoat", "ja": "身代わりにされる" },
      { "en": "blame a scapegoat", "ja": "身代わりを責める" },
      { "en": "look for a scapegoat", "ja": "身代わりを探す" }
    ],
    "related": [
      { "en": "fall guy", "ja": "身代わり(口語)" },
      { "en": "victim", "ja": "犠牲者" },
      { "en": "blame", "ja": "責める" },
      { "en": "patsy", "ja": "だまされ役" }
    ],
    "faq": [
      { "q": "scapegoat の意味は？", "a": "「(他人の罪・失敗の)責任を負わされる身代わり」という意味です。動詞で「身代わりにする」とも使います。" },
      { "q": "make a scapegoat of の意味は？", "a": "「〜を身代わりにする・〜に責任をなすりつける」という意味です。" }
    ],
    "quiz": [
      { "q": "\"They used him as a ___ for their mistakes.\"（身代わり）の空所に入るのは？", "A": "scapegoat", "B": "spotlight", "C": "scarecrow", "D": "scoreboard", "correct": "A" },
      { "q": "scapegoat に最も意味が近いのは？", "A": "fall guy", "B": "leader", "C": "hero", "D": "winner", "correct": "A" }
    ]
  },
  {
    "english": "satire",
    "pron": "ˈsætaɪər",
    "kana": "サタイア",
    "hinshi": "名詞",
    "ld_pos": "名詞",
    "ld_etym": "ラテン語 satira（風刺詩）",
    "ld_level": "1級",
    "badges": ["大学〜", "英検1級", "CEFR C1", "難語"],
    "meaning_main": "風刺 ／ 風刺作品",
    "description": "satire（サタイア）の意味は「風刺・風刺作品」。political satire、satirical との関係、語源、例文やクイズで解説。",
    "keywords": ["satire 意味", "political satire", "satirical", "satire 使い方", "satire 例文"],
    "meanings": [
      { "hinshi": "【名詞】風刺・皮肉(による批判)", "note": "おかしみで欠点を批判すること。" },
      { "hinshi": "【名詞】風刺作品", "note": "風刺をきかせた文学・劇など。" }
    ],
    "usages": [
      { "title": "① 風刺（satire）", "desc": "皮肉による批判。", "example_en": "The play is a satire on politics.", "example_ja": "その劇は政治への風刺だ。" },
      { "title": "② 政治風刺（political satire）", "desc": "政治を皮肉る。", "example_en": "The show is famous for its political satire.", "example_ja": "その番組は政治風刺で有名だ。" },
      { "title": "③ 風刺的な（satirical）", "desc": "形容詞。", "example_en": "a satirical cartoon", "example_ja": "風刺漫画" }
    ],
    "warn": [
      "形容詞は satirical(風刺的な)、動詞は satirize(風刺する)",
      "「(笑い・皮肉を使って社会・人物を)批判すること」。a satire on/of ... の形"
    ],
    "etym_note": "ラテン語 satira（風刺詩、もとは「(いろいろ詰めた)盛り合わせ」を意味する satura)に由来する。「滑稽さで欠点を批判する作品＝風刺」を表す。",
    "etym_chain": [
      { "node": "satira", "sub": "風刺詩", "era": "ラテン語" },
      { "node": "satire", "sub": "風刺", "era": "現代英語" }
    ],
    "phrases": [
      { "en": "political satire", "ja": "政治風刺" },
      { "en": "social satire", "ja": "社会風刺" },
      { "en": "a satire on", "ja": "〜への風刺" },
      { "en": "biting satire", "ja": "痛烈な風刺" },
      { "en": "a work of satire", "ja": "風刺作品" },
      { "en": "satirical humor", "ja": "風刺のきいたユーモア" }
    ],
    "related": [
      { "en": "satirical", "ja": "風刺的な" },
      { "en": "irony", "ja": "皮肉" },
      { "en": "parody", "ja": "パロディー" },
      { "en": "mockery", "ja": "あざけり" }
    ],
    "faq": [
      { "q": "satire の形容詞・動詞形は？", "a": "形容詞は satirical(風刺的な)、動詞は satirize(風刺する)です。" },
      { "q": "satire と parody の違いは？", "a": "satire は「(笑いで欠点を)批判すること全般」、parody は「(作品を)こっけいにまねること」です。" }
    ],
    "quiz": [
      { "q": "\"The novel is a sharp ___ on modern society.\"（風刺）の空所に入るのは？", "A": "satire", "B": "satin", "C": "saturate", "D": "satellite", "correct": "A" },
      { "q": "satire の形容詞形は？", "A": "satirical", "B": "satirous", "C": "satireful", "D": "satirish", "correct": "A" }
    ]
  },
  {
    "english": "saturate",
    "pron": "ˈsætʃəreɪt",
    "kana": "サチュレイト",
    "hinshi": "動詞",
    "ld_pos": "動詞",
    "ld_etym": "ラテン語 saturare（満たす）",
    "ld_level": "1級",
    "badges": ["大学〜", "英検1級", "CEFR C1", "難語"],
    "meaning_main": "（液体で）びしょぬれにする ／ 飽和させる",
    "description": "saturate（サチュレイト）の意味は「(液体で)びしょぬれにする・(市場などを)飽和させる」。saturated との関係、語源、例文やクイズで解説。",
    "keywords": ["saturate 意味", "saturated", "saturate the market", "saturate 使い方", "saturate 例文"],
    "meanings": [
      { "hinshi": "【動詞】（液体で）びしょぬれにする・しみ込ませる", "note": "すっかり水分を含ませる。" },
      { "hinshi": "【動詞】（市場・空間を）いっぱいにする・飽和させる", "note": "限界まで満たす。" }
    ],
    "usages": [
      { "title": "① びしょぬれにする（saturate）", "desc": "水分で満たす。", "example_en": "The rain saturated the soil.", "example_ja": "雨が土をびしょびしょにした。" },
      { "title": "② 飽和させる（saturate the market）", "desc": "いっぱいにする。", "example_en": "Cheap goods saturated the market.", "example_ja": "安価な品が市場にあふれた。" },
      { "title": "③ 飽和した（saturated）", "desc": "形容詞。", "example_en": "The ground was saturated.", "example_ja": "地面は水浸しだった。" }
    ],
    "warn": [
      "「(液体で)びしょぬれにする」と「(市場などを)飽和させる」の両方で使う",
      "saturated fat(飽和脂肪酸)、a saturated market(飽和市場)。名詞は saturation"
    ],
    "etym_note": "ラテン語 saturare（満たす、satur「満ちた」由来)に由来する。「すっかり満たす＝びしょぬれにする・飽和させる」を表す。satisfy や satiate と語幹が関連。",
    "etym_chain": [
      { "node": "saturare", "sub": "満たす", "era": "ラテン語" },
      { "node": "saturate", "sub": "びしょぬれにする・飽和させる", "era": "現代英語" }
    ],
    "phrases": [
      { "en": "saturate the market", "ja": "市場を飽和させる" },
      { "en": "saturated with water", "ja": "水でびしょぬれの" },
      { "en": "saturated fat", "ja": "飽和脂肪酸" },
      { "en": "a saturated market", "ja": "飽和市場" },
      { "en": "saturate the soil", "ja": "土をびしょぬれにする" },
      { "en": "media saturation", "ja": "メディアの過剰露出" }
    ],
    "related": [
      { "en": "soak", "ja": "びしょぬれにする" },
      { "en": "drench", "ja": "ずぶぬれにする" },
      { "en": "flood", "ja": "あふれさせる" },
      { "en": "fill", "ja": "満たす" }
    ],
    "faq": [
      { "q": "saturate の2つの意味は？", "a": "「(液体で)びしょぬれにする・しみ込ませる」と「(市場・空間を)いっぱいにする・飽和させる」です。" },
      { "q": "saturated fat とは？", "a": "「飽和脂肪酸(動物性脂肪などに多い脂肪)」という栄養用語です。" }
    ],
    "quiz": [
      { "q": "\"Heavy rain ___ the fields.\"（びしょぬれにした）の空所に入るのは？", "A": "saturated", "B": "satisfied", "C": "scattered", "D": "separated", "correct": "A" },
      { "q": "saturate に最も意味が近いのは？", "A": "soak", "B": "dry", "C": "empty", "D": "drain", "correct": "A" }
    ]
  },
  {
    "english": "spectacle",
    "pron": "ˈspektəkl",
    "kana": "スペクタクル",
    "hinshi": "名詞",
    "ld_pos": "名詞",
    "ld_etym": "ラテン語 spectaculum（見せ物）",
    "ld_level": "1級",
    "badges": ["大学〜", "英検1級", "CEFR C1", "難語"],
    "meaning_main": "壮観 ／ 見せ物 ／ （複数で）眼鏡",
    "description": "spectacle（スペクタクル）の意味は「壮観・見せ物・(複数形で)眼鏡」。a magnificent spectacle、make a spectacle of oneself の使い方、語源、例文やクイズで解説。",
    "keywords": ["spectacle 意味", "spectacles 眼鏡", "make a spectacle of oneself", "spectacle 使い方", "spectacle 例文"],
    "meanings": [
      { "hinshi": "【名詞】壮観・見もの・光景", "note": "目を見張る大がかりな光景。" },
      { "hinshi": "【名詞】（複数形 spectacles で）眼鏡", "note": "(やや古風)めがね。" }
    ],
    "usages": [
      { "title": "① 壮観（a spectacle）", "desc": "目を見張る光景。", "example_en": "The fireworks were a magnificent spectacle.", "example_ja": "花火は壮観だった。" },
      { "title": "② 見せ物になる（make a spectacle of oneself）", "desc": "人前で恥をさらす。", "example_en": "He made a spectacle of himself.", "example_ja": "彼は人前で醜態をさらした。" },
      { "title": "③ 眼鏡（spectacles）", "desc": "複数形で。", "example_en": "She wore gold-rimmed spectacles.", "example_ja": "彼女は金縁の眼鏡をかけていた。" }
    ],
    "warn": [
      "単数 a spectacle＝壮観・見もの。複数 spectacles＝眼鏡(やや古風、=glasses)",
      "make a spectacle of oneself で「人前で醜態をさらす・見せ物になる」"
    ],
    "etym_note": "ラテン語 spectaculum（見せ物、spectare「見る」由来)に由来する。「目を見張る光景・見せ物」が基本義。眼鏡(spectacles)は「見るための道具」から。spectator と同語源。",
    "etym_chain": [
      { "node": "spectaculum", "sub": "見せ物", "era": "ラテン語" },
      { "node": "spectacle", "sub": "壮観・眼鏡", "era": "現代英語" }
    ],
    "phrases": [
      { "en": "a magnificent spectacle", "ja": "壮大な光景" },
      { "en": "a sad spectacle", "ja": "痛ましい光景" },
      { "en": "make a spectacle of oneself", "ja": "人前で醜態をさらす" },
      { "en": "a public spectacle", "ja": "公の見せ物" },
      { "en": "wear spectacles", "ja": "眼鏡をかける" },
      { "en": "a spectacle to behold", "ja": "見ものの光景" }
    ],
    "related": [
      { "en": "sight", "ja": "光景" },
      { "en": "display", "ja": "見せること" },
      { "en": "show", "ja": "見せ物" },
      { "en": "glasses", "ja": "眼鏡" }
    ],
    "faq": [
      { "q": "spectacle と spectacles の違いは？", "a": "単数 a spectacle は「壮観・見もの」、複数 spectacles は「眼鏡(やや古風)」です。" },
      { "q": "make a spectacle of oneself の意味は？", "a": "「人前で醜態をさらす・恥をかく・見せ物になる」という意味です。" }
    ],
    "quiz": [
      { "q": "\"The parade was an amazing ___.\"（壮観）の空所に入るのは？", "A": "spectacle", "B": "spectator", "C": "spectrum", "D": "specimen", "correct": "A" },
      { "q": "spectacles（複数形）の意味は？", "A": "眼鏡", "B": "観客", "C": "標本", "D": "範囲", "correct": "A" }
    ]
  },
  {
    "english": "stalemate",
    "pron": "ˈsteɪlmeɪt",
    "kana": "ステイルメイト",
    "hinshi": "名詞",
    "ld_pos": "名詞",
    "ld_etym": "stale（行き詰まった）+ mate（チェス用語）",
    "ld_level": "1級",
    "badges": ["大学〜", "英検1級", "CEFR C1", "難語"],
    "meaning_main": "（交渉などの）行き詰まり ／ こう着状態",
    "description": "stalemate（ステイルメイト）の意味は「(交渉などの)行き詰まり・こう着状態」。reach a stalemate の使い方、語源、例文やクイズで解説。",
    "keywords": ["stalemate 意味", "reach a stalemate", "stalemate こう着", "stalemate 使い方", "stalemate 例文"],
    "meanings": [
      { "hinshi": "【名詞】（交渉・争いの）行き詰まり・こう着状態", "note": "双方が動けず進展しない状態。" }
    ],
    "usages": [
      { "title": "① 行き詰まり（a stalemate）", "desc": "進展しない状態。", "example_en": "The talks reached a stalemate.", "example_ja": "交渉は行き詰まった。" },
      { "title": "② こう着状態（break the stalemate）", "desc": "膠着を打破する。", "example_en": "Neither side could break the stalemate.", "example_ja": "どちらの側もこう着状態を打開できなかった。" },
      { "title": "③ 膠着に陥る（end in stalemate）", "desc": "行き詰まりで終わる。", "example_en": "The negotiations ended in stalemate.", "example_ja": "交渉は物別れに終わった。" }
    ],
    "warn": [
      "reach/break a stalemate(行き詰まる/打開する)が頻出",
      "もとはチェスで「動かせず引き分けになる状態」。deadlock(膠着)と近い"
    ],
    "etym_note": "stale（古い・行き詰まった)とチェスの mate(王手・詰み)を組み合わせた語。チェスで「合法な手がなく引き分けになる状態」を指し、転じて「(交渉などの)行き詰まり」を表す。",
    "etym_chain": [
      { "node": "stale + mate", "sub": "行き詰まった詰み", "era": "近代英語" },
      { "node": "stalemate", "sub": "行き詰まり・こう着", "era": "現代英語" }
    ],
    "phrases": [
      { "en": "reach a stalemate", "ja": "行き詰まる" },
      { "en": "break the stalemate", "ja": "こう着状態を打開する" },
      { "en": "end in stalemate", "ja": "物別れに終わる" },
      { "en": "a political stalemate", "ja": "政治的こう着" },
      { "en": "a complete stalemate", "ja": "完全な行き詰まり" },
      { "en": "resolve the stalemate", "ja": "膠着を解消する" }
    ],
    "related": [
      { "en": "deadlock", "ja": "膠着状態" },
      { "en": "impasse", "ja": "行き詰まり" },
      { "en": "standoff", "ja": "にらみ合い" },
      { "en": "gridlock", "ja": "完全な行き詰まり" }
    ],
    "faq": [
      { "q": "stalemate の語源は？", "a": "チェス用語で「合法な手がなく引き分けになる状態」から来ており、転じて「(交渉などの)行き詰まり」を表します。" },
      { "q": "reach/break a stalemate の意味は？", "a": "reach a stalemate は「行き詰まる」、break a stalemate は「こう着状態を打開する」です。" }
    ],
    "quiz": [
      { "q": "\"The peace talks reached a ___.\"（行き詰まり）の空所に入るのは？", "A": "stalemate", "B": "stalebread", "C": "stalk", "D": "stable", "correct": "A" },
      { "q": "stalemate に最も意味が近いのは？", "A": "deadlock", "B": "progress", "C": "agreement", "D": "solution", "correct": "A" }
    ]
  },
  {
    "english": "standstill",
    "pron": "ˈstændstɪl",
    "kana": "スタンドスティル",
    "hinshi": "名詞",
    "ld_pos": "名詞",
    "ld_etym": "stand（立つ）+ still（静止して）",
    "ld_level": "1級",
    "badges": ["大学〜", "英検1級", "CEFR C1", "難語"],
    "meaning_main": "停止 ／ 行き詰まり",
    "description": "standstill（スタンドスティル）の意味は「(完全な)停止・行き詰まり」。come to a standstill の使い方、語源、例文やクイズで解説。",
    "keywords": ["standstill 意味", "come to a standstill", "at a standstill", "standstill 使い方", "standstill 例文"],
    "meanings": [
      { "hinshi": "【名詞】（動きの）停止・行き詰まり", "note": "完全に止まって動かない状態。" }
    ],
    "usages": [
      { "title": "① 停止する（come to a standstill）", "desc": "完全に止まる。", "example_en": "Traffic came to a standstill.", "example_ja": "交通は完全に止まった。" },
      { "title": "② 停止状態で（at a standstill）", "desc": "止まったまま。", "example_en": "The project is at a standstill.", "example_ja": "そのプロジェクトは止まっている。" },
      { "title": "③ 〜を止める（bring to a standstill）", "desc": "停止させる。", "example_en": "The strike brought the city to a standstill.", "example_ja": "ストで都市機能が停止した。" }
    ],
    "warn": [
      "come to / at / bring to a standstill が頻出。「(完全に)動きが止まること」",
      "交通・生産・交渉などが「止まる・行き詰まる」場面で使う"
    ],
    "etym_note": "stand（立つ・止まる)と still（静止して)の複合語。「立ち止まって動かない状態＝停止・行き詰まり」を表す。",
    "etym_chain": [
      { "node": "stand + still", "sub": "立ち止まって動かない", "era": "近代英語" },
      { "node": "standstill", "sub": "停止・行き詰まり", "era": "現代英語" }
    ],
    "phrases": [
      { "en": "come to a standstill", "ja": "完全に止まる" },
      { "en": "at a standstill", "ja": "停止状態で" },
      { "en": "bring to a standstill", "ja": "〜を止める" },
      { "en": "grind to a standstill", "ja": "次第に止まる" },
      { "en": "a complete standstill", "ja": "完全な停止" },
      { "en": "traffic standstill", "ja": "交通のまひ" }
    ],
    "related": [
      { "en": "halt", "ja": "停止" },
      { "en": "stop", "ja": "停止" },
      { "en": "deadlock", "ja": "膠着状態" },
      { "en": "stalemate", "ja": "行き詰まり" }
    ],
    "faq": [
      { "q": "come to a standstill の意味は？", "a": "「(完全に)止まる・停止する」という意味です。" },
      { "q": "at a standstill の意味は？", "a": "「停止状態で・動かないまま・行き詰まって」という意味です。" }
    ],
    "quiz": [
      { "q": "\"The accident brought traffic to a ___.\"（停止）の空所に入るのは？", "A": "standstill", "B": "standpoint", "C": "standout", "D": "standby", "correct": "A" },
      { "q": "standstill に最も意味が近いのは？", "A": "halt", "B": "movement", "C": "progress", "D": "flow", "correct": "A" }
    ]
  },
  {
    "english": "stationery",
    "pron": "ˈsteɪʃəneri",
    "kana": "ステイショナリー",
    "hinshi": "名詞",
    "ld_pos": "名詞",
    "ld_etym": "stationer（文具商）+ -y",
    "ld_level": "準1級",
    "badges": ["高校〜", "英検準1級", "CEFR B2", "頻出語"],
    "meaning_main": "文房具 ／ 便箋類",
    "description": "stationery（ステイショナリー）の意味は「文房具・便箋類」。stationary（動かない）との違い、語源、例文やクイズで解説。",
    "keywords": ["stationery 意味", "stationery stationary 違い", "stationery 文房具", "stationery 使い方", "stationery 例文"],
    "meanings": [
      { "hinshi": "【名詞】文房具・事務用品・便箋類", "note": "紙・ペンなどの筆記具一式。" }
    ],
    "usages": [
      { "title": "① 文房具（stationery）", "desc": "筆記用具など。", "example_en": "I bought some stationery.", "example_ja": "文房具を買った。" },
      { "title": "② 文具店（a stationery shop）", "desc": "文房具を売る店。", "example_en": "There's a stationery shop nearby.", "example_ja": "近くに文房具店がある。" },
      { "title": "③ 便箋（office stationery）", "desc": "事務用紙類。", "example_en": "We ordered new office stationery.", "example_ja": "新しい事務用品を注文した。" }
    ],
    "warn": [
      "stationery(文房具、-e-)と stationary(動かない・静止した、-a-)を混同しない。スペルに注意",
      "数えられない名詞。a stationery とは言わない"
    ],
    "etym_note": "中世の stationer（定まった店を構える商人＝書籍・文具商)に由来する。当時は行商人と違い「定位置(station)」で商売したことから。その商品＝「文房具」を指すようになった。",
    "etym_chain": [
      { "node": "stationer", "sub": "文具商", "era": "中英語" },
      { "node": "stationery", "sub": "文房具", "era": "現代英語" }
    ],
    "phrases": [
      { "en": "office stationery", "ja": "事務用品" },
      { "en": "a stationery shop", "ja": "文房具店" },
      { "en": "buy stationery", "ja": "文房具を買う" },
      { "en": "personalized stationery", "ja": "名入りの便箋" },
      { "en": "stationery supplies", "ja": "文具類" },
      { "en": "a piece of stationery", "ja": "1枚の便箋" }
    ],
    "related": [
      { "en": "stationary", "ja": "動かない（同音異義）" },
      { "en": "supplies", "ja": "用品" },
      { "en": "notebook", "ja": "ノート" },
      { "en": "pen", "ja": "ペン" }
    ],
    "faq": [
      { "q": "stationery と stationary の違いは？", "a": "stationery(-e-)は「文房具」、stationary(-a-)は「動かない・静止した」です。発音は同じですがつづり・意味が違います。" },
      { "q": "覚え方のコツは？", "a": "stationery の e は envelope(封筒)の e、と覚えると文房具のほうと区別できます。" }
    ],
    "quiz": [
      { "q": "\"I need to buy some ___ like pens and paper.\"（文房具）の空所に入るのは？", "A": "stationery", "B": "stationary", "C": "station", "D": "statue", "correct": "A" },
      { "q": "「動かない」を表すのは stationery / stationary のどちら？", "A": "stationary", "B": "stationery", "C": "どちらも同じ", "D": "どちらも違う", "correct": "A" }
    ]
  },
  {
    "english": "succession",
    "pron": "səkˈseʃn",
    "kana": "サクセッション",
    "hinshi": "名詞",
    "ld_pos": "名詞",
    "ld_etym": "ラテン語 successio（後に続くこと）",
    "ld_level": "1級",
    "badges": ["大学〜", "英検1級", "CEFR C1", "難語"],
    "meaning_main": "連続 ／ 継承 ／ 相続",
    "description": "succession（サクセッション）の意味は「連続・継承・相続」。in succession、the line of succession の使い方、語源、例文やクイズで解説。",
    "keywords": ["succession 意味", "in succession", "line of succession", "succession 使い方", "succession 例文"],
    "meanings": [
      { "hinshi": "【名詞】連続・ひと続き", "note": "次々と続くこと。" },
      { "hinshi": "【名詞】継承・相続・後継", "note": "地位・財産を受け継ぐこと。" }
    ],
    "usages": [
      { "title": "① 連続（in succession）", "desc": "立て続けに。", "example_en": "She won three times in succession.", "example_ja": "彼女は3回連続で優勝した。" },
      { "title": "② 継承（the succession to the throne）", "desc": "王位を継ぐこと。", "example_en": "the succession to the throne", "example_ja": "王位の継承" },
      { "title": "③ 後継順位（the line of succession）", "desc": "継承の順序。", "example_en": "He is next in the line of succession.", "example_ja": "彼は継承順位で次に当たる。" }
    ],
    "warn": [
      "in succession で「連続して・立て続けに」が頻出",
      "「(地位・王位・財産の)継承・相続」の意味もある。動詞 succeed には「成功する」と「継承する」の両義"
    ],
    "etym_note": "ラテン語 successio（後に続くこと、succedere「後に続く」由来)に由来する。「次々と続くこと＝連続」「後を継ぐこと＝継承」を表す。succeed と同語源。",
    "etym_chain": [
      { "node": "successio", "sub": "後に続くこと", "era": "ラテン語" },
      { "node": "succession", "sub": "連続・継承", "era": "現代英語" }
    ],
    "phrases": [
      { "en": "in succession", "ja": "連続して" },
      { "en": "in quick succession", "ja": "立て続けに" },
      { "en": "the line of succession", "ja": "継承順位" },
      { "en": "succession to the throne", "ja": "王位継承" },
      { "en": "a succession of", "ja": "一連の〜" },
      { "en": "business succession", "ja": "事業承継" }
    ],
    "related": [
      { "en": "sequence", "ja": "連続・順序" },
      { "en": "series", "ja": "一連" },
      { "en": "inheritance", "ja": "相続" },
      { "en": "successor", "ja": "後継者" }
    ],
    "faq": [
      { "q": "in succession の意味は？", "a": "「連続して・立て続けに」という意味です。in quick succession で「矢継ぎ早に」となります。" },
      { "q": "succession の2つの意味は？", "a": "「(次々と続く)連続」と「(地位・財産の)継承・相続」です。" }
    ],
    "quiz": [
      { "q": "\"The team won four games in ___.\"（連続）の空所に入るのは？", "A": "succession", "B": "success", "C": "successor", "D": "successive", "correct": "A" },
      { "q": "the line of succession の意味は？", "A": "継承順位", "B": "成功への道", "C": "行列", "D": "境界線", "correct": "A" }
    ]
  }
]
